Metadata-Version: 2.1
Name: lassobbn
Version: 1.0.0
Summary: Learning Bayesian Belief Networks with LASSO
Home-page: https://github.com/oneoffcoder/lassobbn
Author: Jee Vang
Author-email: g@oneoffcoder.com
License: UNKNOWN
Keywords: bayesian belief network,bayesian network,causal learning,causal discovery,lasso regression,structure learning
Platform: UNKNOWN
Classifier: Programming Language :: Python :: 3
Classifier: Operating System :: OS Independent
Classifier: Topic :: Scientific/Engineering :: Artificial Intelligence
Classifier: Intended Audience :: Developers
Classifier: Intended Audience :: Science/Research
Classifier: Development Status :: 5 - Production/Stable
